geosea/.gitattributes
geosea/__init__.py
geosea/bsl.py
geosea/calc.py
geosea/compare_df.py
geosea/correct.py
geosea/est_cont_bsl.py
geosea/functions.py
geosea/hori_bsl-multi.py
geosea/plot_bsl.py
geosea/plot_map.py
geosea/proc_bsl.py
geosea/range_sv.py
geosea/replace.py
geosea/search_df.py
geosea/vert_bsl.py
geosea/read/__init__.py
geosea/read/read.py
geosea/read/read_airpressure.py
geosea/read/read_bsl.py
geosea/read/read_data.py
geosea/read/read_id.py
geosea/read/read_meta.py
geosea/read/read_tides.py
geosea/read/.ipynb_checkpoints/Untitled-checkpoint.ipynb
geosea/read/utils/__init__.py
geosea/read/utils/change2dateindex.py
geosea/read/utils/change_dtype.py
geosea/read/utils/create_df.py
geosea/read/utils/extract_df.py
geosea/read/utils/sql.py
geosea/read/utils/sw.py
geosea-2022.1.2.3.dist-info/METADATA
geosea-2022.1.2.3.dist-info/WHEEL
geosea-2022.1.2.3.dist-info/licenses/LICENSE
geosea-2022.1.2.3.dist-info/RECORD
