Metadata-Version: 2.1
Name: geosea
Version: 2022.1.2.3
Summary: A processing package for seafloor geodesy
Project-URL: Homepage, https://github.com/flpetersen/geosea-app
Author-email: "Dr. Florian Petersen" <florianpetersen@gmx.net>
License: MIT License
Classifier: License :: OSI Approved :: MIT License
Classifier: Operating System :: OS Independent
Classifier: Programming Language :: Python :: 3
Requires-Python: >=3.7
